leap.bitmask_js-0.1.201702281423-py2.7-nspkg.pth
leap/bitmask_js/__init__.py
leap/bitmask_js/public/app.bundle.js
leap/bitmask_js/public/app.bundle.js.map
leap/bitmask_js/public/index.html
leap/bitmask_js/public/css/bootstrap.min.css
leap/bitmask_js/public/css/common.css
leap/bitmask_js/public/fonts/glyphicons-halflings-regular.woff2
leap/bitmask_js/public/img/arrow-down.svg
leap/bitmask_js/public/img/arrow-up.svg
leap/bitmask_js/public/img/cloud.svg
leap/bitmask_js/public/img/disabled.svg
leap/bitmask_js/public/img/envelope.svg
leap/bitmask_js/public/img/error.svg
leap/bitmask_js/public/img/gear.svg
leap/bitmask_js/public/img/mask.svg
leap/bitmask_js/public/img/off.svg
leap/bitmask_js/public/img/on.svg
leap/bitmask_js/public/img/planet.svg
leap/bitmask_js/public/img/unknown.svg
leap/bitmask_js/public/img/user.svg
leap/bitmask_js/public/img/wait.svg
leap/bitmask_js/public/js/zxcvbn.js
leap.bitmask_js-0.1.201702281423.dist-info/DESCRIPTION.rst
leap.bitmask_js-0.1.201702281423.dist-info/METADATA
leap.bitmask_js-0.1.201702281423.dist-info/RECORD
leap.bitmask_js-0.1.201702281423.dist-info/WHEEL
leap.bitmask_js-0.1.201702281423.dist-info/metadata.json
leap.bitmask_js-0.1.201702281423.dist-info/namespace_packages.txt
leap.bitmask_js-0.1.201702281423.dist-info/top_level.txt
