Metadata-Version: 2.0
Name: leap.bitmask-js
Version: 0.1.201702281423
Summary: Bitmask UI
Home-page: http://leap.se
Author: LEAP Encrypted Access Project
Author-email: info@leap.se
License: UNKNOWN
Platform: UNKNOWN
